brofser/browser.py
brofser/__init__.py
brofser-0.0.1.dist-info/DESCRIPTION.rst
brofser-0.0.1.dist-info/METADATA
brofser-0.0.1.dist-info/metadata.json
brofser-0.0.1.dist-info/RECORD
brofser-0.0.1.dist-info/top_level.txt
brofser-0.0.1.dist-info/WHEEL
