Metadata-Version: 2.0
Name: brofser
Version: 0.0.1
Summary: brofser - short description
Home-page: https://github.com/thebjorn/brofser
Author: Bjorn Pettersen
Author-email: bp@datakortet.no
License: UNKNOWN
Platform: UNKNOWN
Classifier: Development Status :: 3 - Alpha
Classifier: Intended Audience :: Developers
Classifier: Programming Language :: Python
Classifier: Programming Language :: Python :: 2
Classifier: Programming Language :: Python :: 2.7
Classifier: Topic :: Software Development :: Libraries
Requires: selenium
